MukeshTheBull/__init__.py
MukeshTheBull-1.2.dist-info/LICENSE.txt
MukeshTheBull-1.2.dist-info/METADATA
MukeshTheBull-1.2.dist-info/WHEEL
MukeshTheBull-1.2.dist-info/top_level.txt
MukeshTheBull-1.2.dist-info/RECORD
