Metadata-Version: 2.1
Name: MukeshTheBull
Version: 1.2
Summary: Welcome to Mukesh the Bulls world, full of milk and fun!!
Author: Friends of Cheeku
License-File: LICENSE.txt
Requires-Dist: Pillow
Requires-Dist: certifi
